MANIFEST.in
README.rst
setup.py
contact_form/__init__.py
contact_form/forms.py
contact_form/models.py
contact_form/tests.py
contact_form/urls.py
contact_form/views.py
contact_form/locale/pt_BR/LC_MESSAGES/django.mo
contact_form/locale/pt_BR/LC_MESSAGES/django.po
contact_form/locale/ru/LC_MESSAGES/django.mo
contact_form/locale/ru/LC_MESSAGES/django.po
contact_form/templates/contact_form/contact.html
contact_form/templates/contact_form/contact_completed.html
contact_form/templates/contact_form/email/contact_form_reply.html
django_contact_form_fc.egg-info/PKG-INFO
django_contact_form_fc.egg-info/SOURCES.txt
django_contact_form_fc.egg-info/dependency_links.txt
django_contact_form_fc.egg-info/not-zip-safe
django_contact_form_fc.egg-info/requires.txt
django_contact_form_fc.egg-info/top_level.txt