Metadata-Version: 1.0
Name: django-contact-form-fc
Version: 0.5.1
Summary: Django Contact Form using class based views.
Home-page: https://github.com/futurecolors/django-contact-form
Author: Ilya Baryshev
Author-email: UNKNOWN
License: UNKNOWN
Platform: UNKNOWN
Classifier: Development Status :: 4 - Beta
Classifier: Environment :: Web Environment
Classifier: Framework :: Django
Classifier: Intended Audience :: Developers
Classifier: License :: OSI Approved :: BSD License
Classifier: Operating System :: OS Independent
Classifier: Programming Language :: Python
Classifier: Topic :: Software Development
Classifier: Topic :: Software Development :: Libraries :: Application Frameworks
